glassalpha/__init__.py
glassalpha/__main__.py
glassalpha/config.py
glassalpha/constants.py
glassalpha/exceptions.py
glassalpha/logging_utils.py
glassalpha/api/__init__.py
glassalpha/api/audit.py
glassalpha/api/from_config.py
glassalpha/api/from_model.py
glassalpha/api/from_predictions.py
glassalpha/api/metrics.py
glassalpha/api/result.py
glassalpha/api/run_audit.py
glassalpha/cli/__init__.py
glassalpha/cli/_output.py
glassalpha/cli/exit_codes.py
glassalpha/cli/main.py
glassalpha/cli/preflight.py
glassalpha/cli/quickstart.py
glassalpha/cli/commands/__init__.py
glassalpha/cli/commands/_shared.py
glassalpha/cli/commands/audit.py
glassalpha/cli/commands/cache.py
glassalpha/cli/commands/config_cmds.py
glassalpha/cli/commands/config_group.py
glassalpha/cli/commands/evidence.py
glassalpha/cli/commands/explain.py
glassalpha/cli/commands/publish_check.py
glassalpha/cli/commands/setup_env.py
glassalpha/cli/commands/system.py
glassalpha/configs/README.md
glassalpha/configs/adult_income.yaml
glassalpha/configs/custom_template.yaml
glassalpha/configs/german_credit.yaml
glassalpha/configs/german_credit_simple.yaml
glassalpha/configs/minimal.yaml
glassalpha/configs/production.yaml
glassalpha/configs/quickstart.yaml
glassalpha/data/__init__.py
glassalpha/data/base.py
glassalpha/data/gen_utils.py
glassalpha/data/schema.py
glassalpha/data/tabular.py
glassalpha/data/utils.py
glassalpha/datasets/__init__.py
glassalpha/datasets/adult_income.py
glassalpha/datasets/ccpa_compliance.py
glassalpha/datasets/customer_segmentation.py
glassalpha/datasets/fraud_detection.py
glassalpha/datasets/gdpr_compliance.py
glassalpha/datasets/german_credit.py
glassalpha/datasets/healthcare_outcomes.py
glassalpha/datasets/insurance_risk.py
glassalpha/evidence/__init__.py
glassalpha/evidence/badge.py
glassalpha/evidence/pack.py
glassalpha/evidence/templates/verification_instructions.txt
glassalpha/explain/__init__.py
glassalpha/explain/base.py
glassalpha/explain/coefficients.py
glassalpha/explain/noop.py
glassalpha-0.2.0.dist-info/licenses/LICENSE
glassalpha-0.2.0.dist-info/licenses/NOTICE
glassalpha-0.2.0.dist-info/METADATA
glassalpha-0.2.0.dist-info/WHEEL
glassalpha-0.2.0.dist-info/entry_points.txt
glassalpha-0.2.0.dist-info/top_level.txt
glassalpha-0.2.0.dist-info/RECORD
