Metadata-Version: 2.4
Name: glassalpha
Version: 0.2.0
Summary: AI Compliance Toolkit - transparent, auditable, regulator-ready ML audits
Author: GlassAlpha Team
License-Expression: Apache-2.0
Classifier: Development Status :: 3 - Alpha
Classifier: Intended Audience :: Developers
Classifier: Intended Audience :: Science/Research
Classifier: Intended Audience :: Education
Classifier: Intended Audience :: Information Technology
Classifier: Intended Audience :: Legal Industry
Classifier: Intended Audience :: Financial and Insurance Industry
Classifier: Intended Audience :: Healthcare Industry
Classifier: Topic :: Scientific/Engineering :: Artificial Intelligence
Classifier: Topic :: Software Development :: Quality Assurance
Classifier: Programming Language :: Python :: 3.11
Classifier: Programming Language :: Python :: 3.12
Classifier: Programming Language :: Python :: 3.13
Requires-Python: >=3.11
License-File: LICENSE
License-File: NOTICE
Requires-Dist: typer>=0.9.0
Requires-Dist: pydantic>=2.5.0
Requires-Dist: pyyaml>=6.0
Requires-Dist: numpy>=2.1
Requires-Dist: pandas>=2.2.3
Requires-Dist: scipy>=1.15
Requires-Dist: scikit-learn>=1.5
Requires-Dist: matplotlib>=3.9
Requires-Dist: pillow>=10.0
Requires-Dist: platformdirs>=4.0.0
Requires-Dist: jinja2<4,>=3.1
Provides-Extra: tree-models
Requires-Dist: xgboost>=2.0; extra == "tree-models"
Requires-Dist: lightgbm>=4.0; extra == "tree-models"
Provides-Extra: shap
Requires-Dist: shap>=0.44; extra == "shap"
Provides-Extra: pdf
Requires-Dist: playwright>=1.40; extra == "pdf"
Requires-Dist: weasyprint>=60.0; extra == "pdf"
Requires-Dist: pillow>=10.0; extra == "pdf"
Provides-Extra: dev
Requires-Dist: pytest>=8.0; extra == "dev"
Requires-Dist: pytest-cov>=4.1; extra == "dev"
Requires-Dist: pytest-asyncio>=0.21; extra == "dev"
Requires-Dist: pytest-timeout>=2.2; extra == "dev"
Requires-Dist: hypothesis>=6.92; extra == "dev"
Requires-Dist: nbmake>=1.5; extra == "dev"
Requires-Dist: black>=23.0; extra == "dev"
Requires-Dist: ruff>=0.6; extra == "dev"
Requires-Dist: mypy>=1.11; extra == "dev"
Requires-Dist: yamllint>=1.35; extra == "dev"
Requires-Dist: pre-commit>=3.5; extra == "dev"
Requires-Dist: build>=1.0; extra == "dev"
Requires-Dist: types-PyYAML>=6.0.12; extra == "dev"
Provides-Extra: all
Requires-Dist: glassalpha[pdf,shap,tree_models]; extra == "all"
Provides-Extra: xgboost
Requires-Dist: glassalpha[tree_models]; extra == "xgboost"
Provides-Extra: lightgbm
Requires-Dist: glassalpha[tree_models]; extra == "lightgbm"
Provides-Extra: explain
Requires-Dist: glassalpha[shap,tree_models]; extra == "explain"
Provides-Extra: pdf-all
Requires-Dist: glassalpha[pdf]; extra == "pdf-all"
Provides-Extra: docs
Requires-Dist: glassalpha[pdf]; extra == "docs"
Dynamic: license-file
